ipdon/IPdon.py
ipdon/__init__.py
ipdon-1.0.8.dist-info/LICENSE
ipdon-1.0.8.dist-info/METADATA
ipdon-1.0.8.dist-info/WHEEL
ipdon-1.0.8.dist-info/top_level.txt
ipdon-1.0.8.dist-info/RECORD
