Metadata-Version: 2.1
Name: ipdon
Version: 1.0.8
Summary: IPdon is a low-latency IP intelligence API for Python
Home-page: https://github.com/cwittenberg/ipdon/tree/main/python
Author: Christian
Author-email: christian@ipdon.com
License: MIT
Project-URL: Bug Tracker, https://github.com/cwittenberg/ipdon/issues
Requires-Python: >=3.6
License-File: LICENSE
Requires-Dist: orjson
Requires-Dist: requests
